Workbook

Sheet README
B2: STARLIGHT INTELLIGENCE
B3: 36-Month Revenue Simulator
B4: Modeled 2026-06-26 · price points benchmarked to Mem0 / Letta / Zep + repo docs/monetization-tiers.md
B6: HOW TO USE
B7: 1. Set scenario | C7: On Dashboard, cell C3: type 1 (Bear), 2 (Base), or 3 (Bull). Headline KPIs switch to that scenario.
B8: 2. Tune assumptions | C8: On Assumptions, edit the BLUE cells (Bear/Base/Bull columns). Every blue cell is a lever you control.
B9: 3. Recalculate | C9: If you edit in Excel it recalcs automatically. In LibreOffice press Ctrl+Shift+F9.
B10: 4. Read results | C10: Dashboard = headline + scenario comparison + charts. Calc_* sheets = the month-by-month engine per scenario.
B12: COLOR LEGEND
B13: Blue text | C13: Hardcoded input you change (assumptions / scenario toggle).
B14: Black text | C14: Formula / calculation — don't overwrite.
B15: Green text | C15: Pulls a value from another sheet.
B16: Yellow fill | C16: Key cell that drives everything — the scenario toggle.
B18: THE MODEL IN ONE PICTURE
B19: Funnel | C19: Active installs · Email subscribers · Service leads — each grows monthly at the rate you set.
B20: 5 revenue streams | C20: A Supporter license (one-time) · B Open-core Pro (recurring) · C Managed Cloud (recurring) · E Content+Community (mixed) · D Estate Factory services (project + retainer).
B21: Each stream | C21: =a funnel denominator × a conversion % × a price. All three are blue inputs.
B22: Outputs | C22: Total monthly revenue, Recurring MRR, Cumulative revenue → summed into annual Y1/Y2/Y3 figures.
B24: KEY ASSUMPTIONS BUILT IN (Base case)
B25: Wedge | C25: Governed execution (Hermes) + cross-CLI sovereignty — the lane Mem0/Letta/Zep/Cognee do NOT occupy.
B26: Supporter license | C26: $29 one-time individual (Immich/FUTO model). Voluntary OSS conversion ~1-5% of active users — a runway layer, not the business.
B27: Open-core Pro | C27: $25/seat/mo (between Letta $20 and LangSmith $39). Gates only hosted/multiplayer features, never local memory.
B28: Estate Factory | C28: $25k blended project ACV + $3.5k/mo retainer. This is the near-term CASH ENGINE; OSS+Pro are top-of-funnel.
B29: Sequencing | C29: Service -> Templates -> Community -> Platform. Don't lead with self-serve SaaS.
B31: HONEST CAVEATS
B32: This is a model | C32: Every number is an assumption you can change. It is a thinking instrument, not a forecast. Re-run it weekly against real funnel data.
B33: Biggest lever | C33: Sensitivity (see Dashboard) shows service close-rate and email-list growth move the outcome far more than any price. Distribution, not pricing, is the constraint.
B34: Retrieval gap | C34: Starlight is bm25-only today (no embeddings yet). Model assumes you compete on architecture/governance, not memory recall, until sqlite-vec ships.

Sheet Dashboard
B2: STARLIGHT INTELLIGENCE — REVENUE DASHBOARD
B3: Scenario (1=Bear 2=Base 3=Bull): | C3: =Assumptions!D2 | D3: =CHOOSE(Assumptions!D2,"BEAR","BASE","BULL")
B5: SCENARIO COMPARISON | C5: Bear | D5: Base | E5: Bull
B6: Year 1 revenue | C6: =SUMIF('Calc_Bear'!$C$3:$AL$3,1,'Calc_Bear'!$C$31:$AL$31) | D6: =SUMIF('Calc_Base'!$C$3:$AL$3,1,'Calc_Base'!$C$31:$AL$31) | E6: =SUMIF('Calc_Bull'!$C$3:$AL$3,1,'Calc_Bull'!$C$31:$AL$31)
B7: Year 2 revenue | C7: =SUMIF('Calc_Bear'!$C$3:$AL$3,2,'Calc_Bear'!$C$31:$AL$31) | D7: =SUMIF('Calc_Base'!$C$3:$AL$3,2,'Calc_Base'!$C$31:$AL$31) | E7: =SUMIF('Calc_Bull'!$C$3:$AL$3,2,'Calc_Bull'!$C$31:$AL$31)
B8: Year 3 revenue | C8: =SUMIF('Calc_Bear'!$C$3:$AL$3,3,'Calc_Bear'!$C$31:$AL$31) | D8: =SUMIF('Calc_Base'!$C$3:$AL$3,3,'Calc_Base'!$C$31:$AL$31) | E8: =SUMIF('Calc_Bull'!$C$3:$AL$3,3,'Calc_Bull'!$C$31:$AL$31)
B9: 3-year cumulative | C9: ='Calc_Bear'!$AL$33 | D9: ='Calc_Base'!$AL$33 | E9: ='Calc_Bull'!$AL$33
B10: Exit MRR (month 12) | C10: ='Calc_Bear'!$N$32 | D10: ='Calc_Base'!$N$32 | E10: ='Calc_Bull'!$N$32
B11: Exit MRR (month 36) | C11: ='Calc_Bear'!$AL$32 | D11: ='Calc_Base'!$AL$32 | E11: ='Calc_Bull'!$AL$32
B13: ACTIVE-SCENARIO HEADLINE
B14: Year 1 revenue | C14: =CHOOSE($C$3,C6,D6,E6)
B15: Year 2 revenue | C15: =CHOOSE($C$3,C7,D7,E7)
B16: Year 3 revenue | C16: =CHOOSE($C$3,C8,D8,E8)
B17: 3-year cumulative | C17: =CHOOSE($C$3,C9,D9,E9)
B18: Exit MRR (month 36) | C18: =CHOOSE($C$3,C11,D11,E11)
B20: REVENUE MIX BY YEAR (Base) | C20: Year 1 | D20: Year 2 | E20: Year 3
B21: Supporter | C21: =SUMIF('Calc_Base'!$C$3:$AL$3,1,'Calc_Base'!$C$35:$AL$35) | D21: =SUMIF('Calc_Base'!$C$3:$AL$3,2,'Calc_Base'!$C$35:$AL$35) | E21: =SUMIF('Calc_Base'!$C$3:$AL$3,3,'Calc_Base'!$C$35:$AL$35)
B22: Pro | C22: =SUMIF('Calc_Base'!$C$3:$AL$3,1,'Calc_Base'!$C$36:$AL$36) | D22: =SUMIF('Calc_Base'!$C$3:$AL$3,2,'Calc_Base'!$C$36:$AL$36) | E22: =SUMIF('Calc_Base'!$C$3:$AL$3,3,'Calc_Base'!$C$36:$AL$36)
B23: Cloud | C23: =SUMIF('Calc_Base'!$C$3:$AL$3,1,'Calc_Base'!$C$37:$AL$37) | D23: =SUMIF('Calc_Base'!$C$3:$AL$3,2,'Calc_Base'!$C$37:$AL$37) | E23: =SUMIF('Calc_Base'!$C$3:$AL$3,3,'Calc_Base'!$C$37:$AL$37)
B24: Content | C24: =SUMIF('Calc_Base'!$C$3:$AL$3,1,'Calc_Base'!$C$38:$AL$38) | D24: =SUMIF('Calc_Base'!$C$3:$AL$3,2,'Calc_Base'!$C$38:$AL$38) | E24: =SUMIF('Calc_Base'!$C$3:$AL$3,3,'Calc_Base'!$C$38:$AL$38)
B25: Services | C25: =SUMIF('Calc_Base'!$C$3:$AL$3,1,'Calc_Base'!$C$39:$AL$39) | D25: =SUMIF('Calc_Base'!$C$3:$AL$3,2,'Calc_Base'!$C$39:$AL$39) | E25: =SUMIF('Calc_Base'!$C$3:$AL$3,3,'Calc_Base'!$C$39:$AL$39)

Sheet Assumptions
A1: ASSUMPTIONS — edit BLUE cells
A2: Scenario toggle (1=Bear, 2=Base, 3=Bull) -> used by Dashboard headline: | D2: 2
A4: Lever | B4: Bear | C4: Base | D4: Bull | F4: Unit / Notes
A5: FUNNEL — Active installs (start, month 1) | B5: 150 | C5: 300 | D5: 600 | F5: Agent fleets with vaults initialized
A6: Installs — monthly growth % | B6: 0.07 | C6: 0.1 | D6: 0.15 | F6: Compounding MoM (tapered by decay)
A7: FUNNEL — Email subscribers (start) | B7: 200 | C7: 500 | D7: 1000 | F7: List feeding content/community
A8: Email — monthly growth % | B8: 0.05 | C8: 0.09 | D8: 0.13 | F8: Compounding MoM (tapered by decay)
A9: FUNNEL — Service leads / month (start) | B9: 1.2 | C9: 2 | D9: 2 | F9: Estate Factory inbound
A10: Service leads — monthly growth % | B10: 0.02 | C10: 0.05 | D10: 0.07 | F10: Compounding MoM (tapered by decay)
A11: Funnel growth — monthly decay factor | B11: 0.96 | C11: 0.95 | D11: 0.93 | F11: S-curve: effective growth = g x decay^(month-1). <1 tapers.
A12: [A] Supporter — monthly conversion % of installs | B12: 0.0015 | C12: 0.003 | D12: 0.005 | F12: Voluntary pay (Immich/FUTO); ~1-5%/yr
A13: [A] Supporter — avg one-time payment $ | B13: 30 | C13: 35 | D13: 45 | F13: Blend of $29 individual / $99-149 team
A15: [B] Pro — launch month (1-36) | B15: 9 | C15: 6 | D15: 4 | F15: When self-serve Pro turns on
A16: [B] Pro — trial starts % of installs / month | B16: 0.015 | C16: 0.03 | D16: 0.05
A17: [B] Pro — trial -> paid conversion % | B17: 0.08 | C17: 0.12 | D17: 0.18
A18: [B] Pro — price per seat / month $ | B18: 20 | C18: 25 | D18: 30 | F18: Letta $20 / LangSmith $39 anchors
A19: [B] Pro — monthly churn % | B19: 0.06 | C19: 0.04 | D19: 0.03
A21: [C] Cloud — launch month (1-36) | B21: 24 | C21: 18 | D21: 12 | F21: Managed substrate; later stage
A22: [C] Cloud — attach % of paid seats | B22: 0.2 | C22: 0.3 | D22: 0.45
A23: [C] Cloud — avg $ / seat / month | B23: 40 | C23: 60 | D23: 90 | F23: Usage-based managed runners
A25: [E] Community — new joins % of email / month | B25: 0.004 | C25: 0.008 | D25: 0.013 | F25: Flow into paid community
A26: [E] Community — price / month $ | B26: 15 | C26: 20 | D26: 25
A27: [E] Community — monthly churn % | B27: 0.08 | C27: 0.06 | D27: 0.04
A28: [E] Course — monthly conversion % of email | B28: 0.003 | C28: 0.006 | D28: 0.01 | F28: Evergreen cohort/course sales
A29: [E] Course — price / seat $ | B29: 150 | C29: 250 | D29: 400
A31: [D] Services — lead -> discovery call % | B31: 0.4 | C31: 0.55 | D31: 0.65
A32: [D] Services — call -> close % | B32: 0.16 | C32: 0.25 | D32: 0.28
A33: [D] Services — avg project ACV $ | B33: 15000 | C33: 25000 | D33: 38000 | F33: Estate commission (repo: EUR25-75k)
A34: [D] Services — retainer attach % of closes | B34: 0.3 | C34: 0.5 | D34: 0.65
A35: [D] Services — retainer $ / month | B35: 2000 | C35: 3500 | D35: 5000 | F35: Steward retainer (repo: EUR1.5-5k/mo)
A36: [D] Services — retainer monthly churn % | B36: 0.08 | C36: 0.05 | D36: 0.03

Sheet Sensitivity
B2: SENSITIVITY — which levers move Year-3 revenue most
B3: Year-3 total revenue at each scenario's value for one lever, all else held at Base. Spread = impact.
B5: Driver | C5: Bear Y3 | D5: Base Y3 | E5: Bull Y3 | F5: Why it matters
B6: All levers (full scenario) | C6: =SUMIF('Calc_Bear'!$C$3:$AL$3,3,'Calc_Bear'!$C$31:$AL$31) | D6: =SUMIF('Calc_Base'!$C$3:$AL$3,3,'Calc_Base'!$C$31:$AL$31) | E6: =SUMIF('Calc_Bull'!$C$3:$AL$3,3,'Calc_Bull'!$C$31:$AL$31) | F6: Compounding effect of every assumption together — the envelope.
B7: Service close-rate & lead flow | C7: — | D7: — | E7: — | F7: Highest-leverage: each close = $25k + a retainer annuity. Top priority to instrument.
B8: Email-list growth | C8: — | D8: — | E8: — | F8: Compounds into community + course every month; the cheapest scalable lever.
B9: Installs growth | C9: — | D9: — | E9: — | F9: Feeds Pro + supporter; matters more in years 2-3 as Pro compounds.
B10: Pro price & churn | C10: — | D10: — | E10: — | F10: Sets the recurring annuity slope; churn quietly dominates at scale.
B11: Supporter conversion | C11: — | D11: — | E11: — | F11: Near-zero impact — confirms it's a brand layer, not a revenue engine.
B13: To run a true one-at-a-time test: change ONE blue lever on Assumptions for the Base column, recalc, and watch Base Y3 above move.

Sheet Calc_Bear
A1: Bear ENGINE (drives off Assumptions col B)
A2: Month | C2: 1 | D2: 2 | E2: 3 | F2: 4 | G2: 5 | H2: 6 | I2: 7 | J2: 8 | K2: 9 | L2: 10 | M2: 11 | N2: 12 | O2: 13 | P2: 14 | Q2: 15 | R2: 16 | S2: 17 | T2: 18 | U2: 19 | V2: 20 | W2: 21 | X2: 22 | Y2: 23 | Z2: 24 | AA2: 25 | AB2: 26 | AC2: 27 | AD2: 28 | AE2: 29 | AF2: 30 | AG2: 31 | AH2: 32 | AI2: 33 | AJ2: 34 | AK2: 35 | AL2: 36
A3: Year | C3: 1 | D3: 1 | E3: 1 | F3: 1 | G3: 1 | H3: 1 | I3: 1 | J3: 1 | K3: 1 | L3: 1 | M3: 1 | N3: 1 | O3: 2 | P3: 2 | Q3: 2 | R3: 2 | S3: 2 | T3: 2 | U3: 2 | V3: 2 | W3: 2 | X3: 2 | Y3: 2 | Z3: 2 | AA3: 3 | AB3: 3 | AC3: 3 | AD3: 3 | AE3: 3 | AF3: 3 | AG3: 3 | AH3: 3 | AI3: 3 | AJ3: 3 | AK3: 3 | AL3: 3
A5: Active installs | C5: =Assumptions!$B$5 | D5: =C5*(1+Assumptions!$B$6*POWER(Assumptions!$B$11,D2-1)) | E5: =D5*(1+Assumptions!$B$6*POWER(Assumptions!$B$11,E2-1)) | F5: =E5*(1+Assumptions!$B$6*POWER(Assumptions!$B$11,F2-1)) | G5: =F5*(1+Assumptions!$B$6*POWER(Assumptions!$B$11,G2-1)) | H5: =G5*(1+Assumptions!$B$6*POWER(Assumptions!$B$11,H2-1)) | I5: =H5*(1+Assumptions!$B$6*POWER(Assumptions!$B$11,I2-1)) | J5: =I5*(1+Assumptions!$B$6*POWER(Assumptions!$B$11,J2-1)) | K5: =J5*(1+Assumptions!$B$6*POWER(Assumptions!$B$11,K2-1)) | ... AL5: =AK5*(1+Assumptions!$B$6*POWER(Assumptions!$B$11,AL2-1))
A6: Email subscribers | C6: =Assumptions!$B$7 | D6: =C6*(1+Assumptions!$B$8*POWER(Assumptions!$B$11,D2-1)) | E6: =D6*(1+Assumptions!$B$8*POWER(Assumptions!$B$11,E2-1)) | F6: =E6*(1+Assumptions!$B$8*POWER(Assumptions!$B$11,F2-1)) | G6: =F6*(1+Assumptions!$B$8*POWER(Assumptions!$B$11,G2-1)) | H6: =G6*(1+Assumptions!$B$8*POWER(Assumptions!$B$11,H2-1)) | I6: =H6*(1+Assumptions!$B$8*POWER(Assumptions!$B$11,I2-1)) | J6: =I6*(1+Assumptions!$B$8*POWER(Assumptions!$B$11,J2-1)) | K6: =J6*(1+Assumptions!$B$8*POWER(Assumptions!$B$11,K2-1)) | ... AL6: =AK6*(1+Assumptions!$B$8*POWER(Assumptions!$B$11,AL2-1))
A7: Service leads / mo | C7: =Assumptions!$B$9 | D7: =C7*(1+Assumptions!$B$10*POWER(Assumptions!$B$11,D2-1)) | E7: =D7*(1+Assumptions!$B$10*POWER(Assumptions!$B$11,E2-1)) | F7: =E7*(1+Assumptions!$B$10*POWER(Assumptions!$B$11,F2-1)) | G7: =F7*(1+Assumptions!$B$10*POWER(Assumptions!$B$11,G2-1)) | H7: =G7*(1+Assumptions!$B$10*POWER(Assumptions!$B$11,H2-1)) | I7: =H7*(1+Assumptions!$B$10*POWER(Assumptions!$B$11,I2-1)) | J7: =I7*(1+Assumptions!$B$10*POWER(Assumptions!$B$11,J2-1)) | K7: =J7*(1+Assumptions!$B$10*POWER(Assumptions!$B$11,K2-1)) | ... AL7: =AK7*(1+Assumptions!$B$10*POWER(Assumptions!$B$11,AL2-1))
A9: [A] New supporter payers | C9: =C5*Assumptions!$B$12 | D9: =D5*Assumptions!$B$12 | E9: =E5*Assumptions!$B$12 | F9: =F5*Assumptions!$B$12 | G9: =G5*Assumptions!$B$12 | H9: =H5*Assumptions!$B$12 | I9: =I5*Assumptions!$B$12 | J9: =J5*Assumptions!$B$12 | ... AL9: =AL5*Assumptions!$B$12
A10: [A] Supporter revenue | C10: =C9*Assumptions!$B$13 | D10: =D9*Assumptions!$B$13 | E10: =E9*Assumptions!$B$13 | F10: =F9*Assumptions!$B$13 | G10: =G9*Assumptions!$B$13 | H10: =H9*Assumptions!$B$13 | I10: =I9*Assumptions!$B$13 | J10: =J9*Assumptions!$B$13 | ... AL10: =AL9*Assumptions!$B$13
A12: [B] Pro trials | C12: =IF(C2>=Assumptions!$B$15,C5*Assumptions!$B$16,0) | D12: =IF(D2>=Assumptions!$B$15,D5*Assumptions!$B$16,0) | E12: =IF(E2>=Assumptions!$B$15,E5*Assumptions!$B$16,0) | F12: =IF(F2>=Assumptions!$B$15,F5*Assumptions!$B$16,0) | G12: =IF(G2>=Assumptions!$B$15,G5*Assumptions!$B$16,0) | H12: =IF(H2>=Assumptions!$B$15,H5*Assumptions!$B$16,0) | I12: =IF(I2>=Assumptions!$B$15,I5*Assumptions!$B$16,0) | J12: =IF(J2>=Assumptions!$B$15,J5*Assumptions!$B$16,0) | ... AL12: =IF(AL2>=Assumptions!$B$15,AL5*Assumptions!$B$16,0)
A13: [B] New paid seats | C13: =C12*Assumptions!$B$17 | D13: =D12*Assumptions!$B$17 | E13: =E12*Assumptions!$B$17 | F13: =F12*Assumptions!$B$17 | G13: =G12*Assumptions!$B$17 | H13: =H12*Assumptions!$B$17 | I13: =I12*Assumptions!$B$17 | J13: =J12*Assumptions!$B$17 | ... AL13: =AL12*Assumptions!$B$17
A14: [B] Active paid seats | C14: =C13 | D14: =C14*(1-Assumptions!$B$19)+D13 | E14: =D14*(1-Assumptions!$B$19)+E13 | F14: =E14*(1-Assumptions!$B$19)+F13 | G14: =F14*(1-Assumptions!$B$19)+G13 | H14: =G14*(1-Assumptions!$B$19)+H13 | I14: =H14*(1-Assumptions!$B$19)+I13 | J14: =I14*(1-Assumptions!$B$19)+J13 | K14: =J14*(1-Assumptions!$B$19)+K13 | ... AL14: =AK14*(1-Assumptions!$B$19)+AL13
A15: [B] Pro MRR | C15: =C14*Assumptions!$B$18 | D15: =D14*Assumptions!$B$18 | E15: =E14*Assumptions!$B$18 | F15: =F14*Assumptions!$B$18 | G15: =G14*Assumptions!$B$18 | H15: =H14*Assumptions!$B$18 | I15: =I14*Assumptions!$B$18 | J15: =J14*Assumptions!$B$18 | ... AL15: =AL14*Assumptions!$B$18
A17: [C] Cloud MRR | C17: =IF(C2>=Assumptions!$B$21,C14*Assumptions!$B$22*Assumptions!$B$23,0) | D17: =IF(D2>=Assumptions!$B$21,D14*Assumptions!$B$22*Assumptions!$B$23,0) | E17: =IF(E2>=Assumptions!$B$21,E14*Assumptions!$B$22*Assumptions!$B$23,0) | F17: =IF(F2>=Assumptions!$B$21,F14*Assumptions!$B$22*Assumptions!$B$23,0) | G17: =IF(G2>=Assumptions!$B$21,G14*Assumptions!$B$22*Assumptions!$B$23,0) | H17: =IF(H2>=Assumptions!$B$21,H14*Assumptions!$B$22*Assumptions!$B$23,0) | I17: =IF(I2>=Assumptions!$B$21,I14*Assumptions!$B$22*Assumptions!$B$23,0) | J17: =IF(J2>=Assumptions!$B$21,J14*Assumptions!$B$22*Assumptions!$B$23,0) | ... AL17: =IF(AL2>=Assumptions!$B$21,AL14*Assumptions!$B$22*Assumptions!$B$23,0)
A19: [E] New community members | C19: =C6*Assumptions!$B$25 | D19: =D6*Assumptions!$B$25 | E19: =E6*Assumptions!$B$25 | F19: =F6*Assumptions!$B$25 | G19: =G6*Assumptions!$B$25 | H19: =H6*Assumptions!$B$25 | I19: =I6*Assumptions!$B$25 | J19: =J6*Assumptions!$B$25 | ... AL19: =AL6*Assumptions!$B$25
A20: [E] Active community | C20: =C19 | D20: =C20*(1-Assumptions!$B$27)+D19 | E20: =D20*(1-Assumptions!$B$27)+E19 | F20: =E20*(1-Assumptions!$B$27)+F19 | G20: =F20*(1-Assumptions!$B$27)+G19 | H20: =G20*(1-Assumptions!$B$27)+H19 | I20: =H20*(1-Assumptions!$B$27)+I19 | J20: =I20*(1-Assumptions!$B$27)+J19 | K20: =J20*(1-Assumptions!$B$27)+K19 | ... AL20: =AK20*(1-Assumptions!$B$27)+AL19
A21: [E] Community MRR | C21: =C20*Assumptions!$B$26 | D21: =D20*Assumptions!$B$26 | E21: =E20*Assumptions!$B$26 | F21: =F20*Assumptions!$B$26 | G21: =G20*Assumptions!$B$26 | H21: =H20*Assumptions!$B$26 | I21: =I20*Assumptions!$B$26 | J21: =J20*Assumptions!$B$26 | ... AL21: =AL20*Assumptions!$B$26
A22: [E] Course revenue | C22: =C6*Assumptions!$B$28*Assumptions!$B$29 | D22: =D6*Assumptions!$B$28*Assumptions!$B$29 | E22: =E6*Assumptions!$B$28*Assumptions!$B$29 | F22: =F6*Assumptions!$B$28*Assumptions!$B$29 | G22: =G6*Assumptions!$B$28*Assumptions!$B$29 | H22: =H6*Assumptions!$B$28*Assumptions!$B$29 | I22: =I6*Assumptions!$B$28*Assumptions!$B$29 | J22: =J6*Assumptions!$B$28*Assumptions!$B$29 | ... AL22: =AL6*Assumptions!$B$28*Assumptions!$B$29
A24: [D] Discovery calls | C24: =C7*Assumptions!$B$31 | D24: =D7*Assumptions!$B$31 | E24: =E7*Assumptions!$B$31 | F24: =F7*Assumptions!$B$31 | G24: =G7*Assumptions!$B$31 | H24: =H7*Assumptions!$B$31 | I24: =I7*Assumptions!$B$31 | J24: =J7*Assumptions!$B$31 | ... AL24: =AL7*Assumptions!$B$31
A25: [D] New projects | C25: =C24*Assumptions!$B$32 | D25: =D24*Assumptions!$B$32 | E25: =E24*Assumptions!$B$32 | F25: =F24*Assumptions!$B$32 | G25: =G24*Assumptions!$B$32 | H25: =H24*Assumptions!$B$32 | I25: =I24*Assumptions!$B$32 | J25: =J24*Assumptions!$B$32 | ... AL25: =AL24*Assumptions!$B$32
A26: [D] Project revenue | C26: =C25*Assumptions!$B$33 | D26: =D25*Assumptions!$B$33 | E26: =E25*Assumptions!$B$33 | F26: =F25*Assumptions!$B$33 | G26: =G25*Assumptions!$B$33 | H26: =H25*Assumptions!$B$33 | I26: =I25*Assumptions!$B$33 | J26: =J25*Assumptions!$B$33 | ... AL26: =AL25*Assumptions!$B$33
A27: [D] New retainers | C27: =C25*Assumptions!$B$34 | D27: =D25*Assumptions!$B$34 | E27: =E25*Assumptions!$B$34 | F27: =F25*Assumptions!$B$34 | G27: =G25*Assumptions!$B$34 | H27: =H25*Assumptions!$B$34 | I27: =I25*Assumptions!$B$34 | J27: =J25*Assumptions!$B$34 | ... AL27: =AL25*Assumptions!$B$34
A28: [D] Active retainers | C28: =C27 | D28: =C28*(1-Assumptions!$B$36)+D27 | E28: =D28*(1-Assumptions!$B$36)+E27 | F28: =E28*(1-Assumptions!$B$36)+F27 | G28: =F28*(1-Assumptions!$B$36)+G27 | H28: =G28*(1-Assumptions!$B$36)+H27 | I28: =H28*(1-Assumptions!$B$36)+I27 | J28: =I28*(1-Assumptions!$B$36)+J27 | K28: =J28*(1-Assumptions!$B$36)+K27 | ... AL28: =AK28*(1-Assumptions!$B$36)+AL27
A29: [D] Retainer MRR | C29: =C28*Assumptions!$B$35 | D29: =D28*Assumptions!$B$35 | E29: =E28*Assumptions!$B$35 | F29: =F28*Assumptions!$B$35 | G29: =G28*Assumptions!$B$35 | H29: =H28*Assumptions!$B$35 | I29: =I28*Assumptions!$B$35 | J29: =J28*Assumptions!$B$35 | ... AL29: =AL28*Assumptions!$B$35
A31: TOTAL monthly revenue | C31: =C10+C15+C17+C21+C22+C26+C29 | D31: =D10+D15+D17+D21+D22+D26+D29 | E31: =E10+E15+E17+E21+E22+E26+E29 | F31: =F10+F15+F17+F21+F22+F26+F29 | G31: =G10+G15+G17+G21+G22+G26+G29 | H31: =H10+H15+H17+H21+H22+H26+H29 | I31: =I10+I15+I17+I21+I22+I26+I29 | J31: =J10+J15+J17+J21+J22+J26+J29 | ... AL31: =AL10+AL15+AL17+AL21+AL22+AL26+AL29
A32: Recurring MRR | C32: =C15+C17+C21+C29 | D32: =D15+D17+D21+D29 | E32: =E15+E17+E21+E29 | F32: =F15+F17+F21+F29 | G32: =G15+G17+G21+G29 | H32: =H15+H17+H21+H29 | I32: =I15+I17+I21+I29 | J32: =J15+J17+J21+J29 | ... AL32: =AL15+AL17+AL21+AL29
A33: Cumulative revenue | C33: =C31 | D33: =C33+D31 | E33: =D33+E31 | F33: =E33+F31 | G33: =F33+G31 | H33: =G33+H31 | I33: =H33+I31 | J33: =I33+J31 | K33: =J33+K31 | ... AL33: =AK33+AL31
A35: mix: Supporter | C35: =C10 | D35: =D10 | E35: =E10 | F35: =F10 | G35: =G10 | H35: =H10 | I35: =I10 | J35: =J10 | ... AL35: =AL10
A36: mix: Pro | C36: =C15 | D36: =D15 | E36: =E15 | F36: =F15 | G36: =G15 | H36: =H15 | I36: =I15 | J36: =J15 | ... AL36: =AL15
A37: mix: Cloud | C37: =C17 | D37: =D17 | E37: =E17 | F37: =F17 | G37: =G17 | H37: =H17 | I37: =I17 | J37: =J17 | ... AL37: =AL17
A38: mix: Content | C38: =C21+C22 | D38: =D21+D22 | E38: =E21+E22 | F38: =F21+F22 | G38: =G21+G22 | H38: =H21+H22 | I38: =I21+I22 | J38: =J21+J22 | ... AL38: =AL21+AL22
A39: mix: Services | C39: =C26+C29 | D39: =D26+D29 | E39: =E26+E29 | F39: =F26+F29 | G39: =G26+G29 | H39: =H26+H29 | I39: =I26+I29 | J39: =J26+J29 | ... AL39: =AL26+AL29

Sheet Calc_Base
A1: Base ENGINE (drives off Assumptions col C)
A2: Month | C2: 1 | D2: 2 | E2: 3 | F2: 4 | G2: 5 | H2: 6 | I2: 7 | J2: 8 | K2: 9 | L2: 10 | M2: 11 | N2: 12 | O2: 13 | P2: 14 | Q2: 15 | R2: 16 | S2: 17 | T2: 18 | U2: 19 | V2: 20 | W2: 21 | X2: 22 | Y2: 23 | Z2: 24 | AA2: 25 | AB2: 26 | AC2: 27 | AD2: 28 | AE2: 29 | AF2: 30 | AG2: 31 | AH2: 32 | AI2: 33 | AJ2: 34 | AK2: 35 | AL2: 36
A3: Year | C3: 1 | D3: 1 | E3: 1 | F3: 1 | G3: 1 | H3: 1 | I3: 1 | J3: 1 | K3: 1 | L3: 1 | M3: 1 | N3: 1 | O3: 2 | P3: 2 | Q3: 2 | R3: 2 | S3: 2 | T3: 2 | U3: 2 | V3: 2 | W3: 2 | X3: 2 | Y3: 2 | Z3: 2 | AA3: 3 | AB3: 3 | AC3: 3 | AD3: 3 | AE3: 3 | AF3: 3 | AG3: 3 | AH3: 3 | AI3: 3 | AJ3: 3 | AK3: 3 | AL3: 3
A5: Active installs | C5: =Assumptions!$C$5 | D5: =C5*(1+Assumptions!$C$6*POWER(Assumptions!$C$11,D2-1)) | E5: =D5*(1+Assumptions!$C$6*POWER(Assumptions!$C$11,E2-1)) | F5: =E5*(1+Assumptions!$C$6*POWER(Assumptions!$C$11,F2-1)) | G5: =F5*(1+Assumptions!$C$6*POWER(Assumptions!$C$11,G2-1)) | H5: =G5*(1+Assumptions!$C$6*POWER(Assumptions!$C$11,H2-1)) | I5: =H5*(1+Assumptions!$C$6*POWER(Assumptions!$C$11,I2-1)) | J5: =I5*(1+Assumptions!$C$6*POWER(Assumptions!$C$11,J2-1)) | K5: =J5*(1+Assumptions!$C$6*POWER(Assumptions!$C$11,K2-1)) | ... AL5: =AK5*(1+Assumptions!$C$6*POWER(Assumptions!$C$11,AL2-1))
A6: Email subscribers | C6: =Assumptions!$C$7 | D6: =C6*(1+Assumptions!$C$8*POWER(Assumptions!$C$11,D2-1)) | E6: =D6*(1+Assumptions!$C$8*POWER(Assumptions!$C$11,E2-1)) | F6: =E6*(1+Assumptions!$C$8*POWER(Assumptions!$C$11,F2-1)) | G6: =F6*(1+Assumptions!$C$8*POWER(Assumptions!$C$11,G2-1)) | H6: =G6*(1+Assumptions!$C$8*POWER(Assumptions!$C$11,H2-1)) | I6: =H6*(1+Assumptions!$C$8*POWER(Assumptions!$C$11,I2-1)) | J6: =I6*(1+Assumptions!$C$8*POWER(Assumptions!$C$11,J2-1)) | K6: =J6*(1+Assumptions!$C$8*POWER(Assumptions!$C$11,K2-1)) | ... AL6: =AK6*(1+Assumptions!$C$8*POWER(Assumptions!$C$11,AL2-1))
A7: Service leads / mo | C7: =Assumptions!$C$9 | D7: =C7*(1+Assumptions!$C$10*POWER(Assumptions!$C$11,D2-1)) | E7: =D7*(1+Assumptions!$C$10*POWER(Assumptions!$C$11,E2-1)) | F7: =E7*(1+Assumptions!$C$10*POWER(Assumptions!$C$11,F2-1)) | G7: =F7*(1+Assumptions!$C$10*POWER(Assumptions!$C$11,G2-1)) | H7: =G7*(1+Assumptions!$C$10*POWER(Assumptions!$C$11,H2-1)) | I7: =H7*(1+Assumptions!$C$10*POWER(Assumptions!$C$11,I2-1)) | J7: =I7*(1+Assumptions!$C$10*POWER(Assumptions!$C$11,J2-1)) | K7: =J7*(1+Assumptions!$C$10*POWER(Assumptions!$C$11,K2-1)) | ... AL7: =AK7*(1+Assumptions!$C$10*POWER(Assumptions!$C$11,AL2-1))
A9: [A] New supporter payers | C9: =C5*Assumptions!$C$12 | D9: =D5*Assumptions!$C$12 | E9: =E5*Assumptions!$C$12 | F9: =F5*Assumptions!$C$12 | G9: =G5*Assumptions!$C$12 | H9: =H5*Assumptions!$C$12 | I9: =I5*Assumptions!$C$12 | J9: =J5*Assumptions!$C$12 | ... AL9: =AL5*Assumptions!$C$12
A10: [A] Supporter revenue | C10: =C9*Assumptions!$C$13 | D10: =D9*Assumptions!$C$13 | E10: =E9*Assumptions!$C$13 | F10: =F9*Assumptions!$C$13 | G10: =G9*Assumptions!$C$13 | H10: =H9*Assumptions!$C$13 | I10: =I9*Assumptions!$C$13 | J10: =J9*Assumptions!$C$13 | ... AL10: =AL9*Assumptions!$C$13
A12: [B] Pro trials | C12: =IF(C2>=Assumptions!$C$15,C5*Assumptions!$C$16,0) | D12: =IF(D2>=Assumptions!$C$15,D5*Assumptions!$C$16,0) | E12: =IF(E2>=Assumptions!$C$15,E5*Assumptions!$C$16,0) | F12: =IF(F2>=Assumptions!$C$15,F5*Assumptions!$C$16,0) | G12: =IF(G2>=Assumptions!$C$15,G5*Assumptions!$C$16,0) | H12: =IF(H2>=Assumptions!$C$15,H5*Assumptions!$C$16,0) | I12: =IF(I2>=Assumptions!$C$15,I5*Assumptions!$C$16,0) | J12: =IF(J2>=Assumptions!$C$15,J5*Assumptions!$C$16,0) | ... AL12: =IF(AL2>=Assumptions!$C$15,AL5*Assumptions!$C$16,0)
A13: [B] New paid seats | C13: =C12*Assumptions!$C$17 | D13: =D12*Assumptions!$C$17 | E13: =E12*Assumptions!$C$17 | F13: =F12*Assumptions!$C$17 | G13: =G12*Assumptions!$C$17 | H13: =H12*Assumptions!$C$17 | I13: =I12*Assumptions!$C$17 | J13: =J12*Assumptions!$C$17 | ... AL13: =AL12*Assumptions!$C$17
A14: [B] Active paid seats | C14: =C13 | D14: =C14*(1-Assumptions!$C$19)+D13 | E14: =D14*(1-Assumptions!$C$19)+E13 | F14: =E14*(1-Assumptions!$C$19)+F13 | G14: =F14*(1-Assumptions!$C$19)+G13 | H14: =G14*(1-Assumptions!$C$19)+H13 | I14: =H14*(1-Assumptions!$C$19)+I13 | J14: =I14*(1-Assumptions!$C$19)+J13 | K14: =J14*(1-Assumptions!$C$19)+K13 | ... AL14: =AK14*(1-Assumptions!$C$19)+AL13
A15: [B] Pro MRR | C15: =C14*Assumptions!$C$18 | D15: =D14*Assumptions!$C$18 | E15: =E14*Assumptions!$C$18 | F15: =F14*Assumptions!$C$18 | G15: =G14*Assumptions!$C$18 | H15: =H14*Assumptions!$C$18 | I15: =I14*Assumptions!$C$18 | J15: =J14*Assumptions!$C$18 | ... AL15: =AL14*Assumptions!$C$18
A17: [C] Cloud MRR | C17: =IF(C2>=Assumptions!$C$21,C14*Assumptions!$C$22*Assumptions!$C$23,0) | D17: =IF(D2>=Assumptions!$C$21,D14*Assumptions!$C$22*Assumptions!$C$23,0) | E17: =IF(E2>=Assumptions!$C$21,E14*Assumptions!$C$22*Assumptions!$C$23,0) | F17: =IF(F2>=Assumptions!$C$21,F14*Assumptions!$C$22*Assumptions!$C$23,0) | G17: =IF(G2>=Assumptions!$C$21,G14*Assumptions!$C$22*Assumptions!$C$23,0) | H17: =IF(H2>=Assumptions!$C$21,H14*Assumptions!$C$22*Assumptions!$C$23,0) | I17: =IF(I2>=Assumptions!$C$21,I14*Assumptions!$C$22*Assumptions!$C$23,0) | J17: =IF(J2>=Assumptions!$C$21,J14*Assumptions!$C$22*Assumptions!$C$23,0) | ... AL17: =IF(AL2>=Assumptions!$C$21,AL14*Assumptions!$C$22*Assumptions!$C$23,0)
A19: [E] New community members | C19: =C6*Assumptions!$C$25 | D19: =D6*Assumptions!$C$25 | E19: =E6*Assumptions!$C$25 | F19: =F6*Assumptions!$C$25 | G19: =G6*Assumptions!$C$25 | H19: =H6*Assumptions!$C$25 | I19: =I6*Assumptions!$C$25 | J19: =J6*Assumptions!$C$25 | ... AL19: =AL6*Assumptions!$C$25
A20: [E] Active community | C20: =C19 | D20: =C20*(1-Assumptions!$C$27)+D19 | E20: =D20*(1-Assumptions!$C$27)+E19 | F20: =E20*(1-Assumptions!$C$27)+F19 | G20: =F20*(1-Assumptions!$C$27)+G19 | H20: =G20*(1-Assumptions!$C$27)+H19 | I20: =H20*(1-Assumptions!$C$27)+I19 | J20: =I20*(1-Assumptions!$C$27)+J19 | K20: =J20*(1-Assumptions!$C$27)+K19 | ... AL20: =AK20*(1-Assumptions!$C$27)+AL19
A21: [E] Community MRR | C21: =C20*Assumptions!$C$26 | D21: =D20*Assumptions!$C$26 | E21: =E20*Assumptions!$C$26 | F21: =F20*Assumptions!$C$26 | G21: =G20*Assumptions!$C$26 | H21: =H20*Assumptions!$C$26 | I21: =I20*Assumptions!$C$26 | J21: =J20*Assumptions!$C$26 | ... AL21: =AL20*Assumptions!$C$26
A22: [E] Course revenue | C22: =C6*Assumptions!$C$28*Assumptions!$C$29 | D22: =D6*Assumptions!$C$28*Assumptions!$C$29 | E22: =E6*Assumptions!$C$28*Assumptions!$C$29 | F22: =F6*Assumptions!$C$28*Assumptions!$C$29 | G22: =G6*Assumptions!$C$28*Assumptions!$C$29 | H22: =H6*Assumptions!$C$28*Assumptions!$C$29 | I22: =I6*Assumptions!$C$28*Assumptions!$C$29 | J22: =J6*Assumptions!$C$28*Assumptions!$C$29 | ... AL22: =AL6*Assumptions!$C$28*Assumptions!$C$29
A24: [D] Discovery calls | C24: =C7*Assumptions!$C$31 | D24: =D7*Assumptions!$C$31 | E24: =E7*Assumptions!$C$31 | F24: =F7*Assumptions!$C$31 | G24: =G7*Assumptions!$C$31 | H24: =H7*Assumptions!$C$31 | I24: =I7*Assumptions!$C$31 | J24: =J7*Assumptions!$C$31 | ... AL24: =AL7*Assumptions!$C$31
A25: [D] New projects | C25: =C24*Assumptions!$C$32 | D25: =D24*Assumptions!$C$32 | E25: =E24*Assumptions!$C$32 | F25: =F24*Assumptions!$C$32 | G25: =G24*Assumptions!$C$32 | H25: =H24*Assumptions!$C$32 | I25: =I24*Assumptions!$C$32 | J25: =J24*Assumptions!$C$32 | ... AL25: =AL24*Assumptions!$C$32
A26: [D] Project revenue | C26: =C25*Assumptions!$C$33 | D26: =D25*Assumptions!$C$33 | E26: =E25*Assumptions!$C$33 | F26: =F25*Assumptions!$C$33 | G26: =G25*Assumptions!$C$33 | H26: =H25*Assumptions!$C$33 | I26: =I25*Assumptions!$C$33 | J26: =J25*Assumptions!$C$33 | ... AL26: =AL25*Assumptions!$C$33
A27: [D] New retainers | C27: =C25*Assumptions!$C$34 | D27: =D25*Assumptions!$C$34 | E27: =E25*Assumptions!$C$34 | F27: =F25*Assumptions!$C$34 | G27: =G25*Assumptions!$C$34 | H27: =H25*Assumptions!$C$34 | I27: =I25*Assumptions!$C$34 | J27: =J25*Assumptions!$C$34 | ... AL27: =AL25*Assumptions!$C$34
A28: [D] Active retainers | C28: =C27 | D28: =C28*(1-Assumptions!$C$36)+D27 | E28: =D28*(1-Assumptions!$C$36)+E27 | F28: =E28*(1-Assumptions!$C$36)+F27 | G28: =F28*(1-Assumptions!$C$36)+G27 | H28: =G28*(1-Assumptions!$C$36)+H27 | I28: =H28*(1-Assumptions!$C$36)+I27 | J28: =I28*(1-Assumptions!$C$36)+J27 | K28: =J28*(1-Assumptions!$C$36)+K27 | ... AL28: =AK28*(1-Assumptions!$C$36)+AL27
A29: [D] Retainer MRR | C29: =C28*Assumptions!$C$35 | D29: =D28*Assumptions!$C$35 | E29: =E28*Assumptions!$C$35 | F29: =F28*Assumptions!$C$35 | G29: =G28*Assumptions!$C$35 | H29: =H28*Assumptions!$C$35 | I29: =I28*Assumptions!$C$35 | J29: =J28*Assumptions!$C$35 | ... AL29: =AL28*Assumptions!$C$35
A31: TOTAL monthly revenue | C31: =C10+C15+C17+C21+C22+C26+C29 | D31: =D10+D15+D17+D21+D22+D26+D29 | E31: =E10+E15+E17+E21+E22+E26+E29 | F31: =F10+F15+F17+F21+F22+F26+F29 | G31: =G10+G15+G17+G21+G22+G26+G29 | H31: =H10+H15+H17+H21+H22+H26+H29 | I31: =I10+I15+I17+I21+I22+I26+I29 | J31: =J10+J15+J17+J21+J22+J26+J29 | ... AL31: =AL10+AL15+AL17+AL21+AL22+AL26+AL29
A32: Recurring MRR | C32: =C15+C17+C21+C29 | D32: =D15+D17+D21+D29 | E32: =E15+E17+E21+E29 | F32: =F15+F17+F21+F29 | G32: =G15+G17+G21+G29 | H32: =H15+H17+H21+H29 | I32: =I15+I17+I21+I29 | J32: =J15+J17+J21+J29 | ... AL32: =AL15+AL17+AL21+AL29
A33: Cumulative revenue | C33: =C31 | D33: =C33+D31 | E33: =D33+E31 | F33: =E33+F31 | G33: =F33+G31 | H33: =G33+H31 | I33: =H33+I31 | J33: =I33+J31 | K33: =J33+K31 | ... AL33: =AK33+AL31
A35: mix: Supporter | C35: =C10 | D35: =D10 | E35: =E10 | F35: =F10 | G35: =G10 | H35: =H10 | I35: =I10 | J35: =J10 | ... AL35: =AL10
A36: mix: Pro | C36: =C15 | D36: =D15 | E36: =E15 | F36: =F15 | G36: =G15 | H36: =H15 | I36: =I15 | J36: =J15 | ... AL36: =AL15
A37: mix: Cloud | C37: =C17 | D37: =D17 | E37: =E17 | F37: =F17 | G37: =G17 | H37: =H17 | I37: =I17 | J37: =J17 | ... AL37: =AL17
A38: mix: Content | C38: =C21+C22 | D38: =D21+D22 | E38: =E21+E22 | F38: =F21+F22 | G38: =G21+G22 | H38: =H21+H22 | I38: =I21+I22 | J38: =J21+J22 | ... AL38: =AL21+AL22
A39: mix: Services | C39: =C26+C29 | D39: =D26+D29 | E39: =E26+E29 | F39: =F26+F29 | G39: =G26+G29 | H39: =H26+H29 | I39: =I26+I29 | J39: =J26+J29 | ... AL39: =AL26+AL29

Sheet Calc_Bull
A1: Bull ENGINE (drives off Assumptions col D)
A2: Month | C2: 1 | D2: 2 | E2: 3 | F2: 4 | G2: 5 | H2: 6 | I2: 7 | J2: 8 | K2: 9 | L2: 10 | M2: 11 | N2: 12 | O2: 13 | P2: 14 | Q2: 15 | R2: 16 | S2: 17 | T2: 18 | U2: 19 | V2: 20 | W2: 21 | X2: 22 | Y2: 23 | Z2: 24 | AA2: 25 | AB2: 26 | AC2: 27 | AD2: 28 | AE2: 29 | AF2: 30 | AG2: 31 | AH2: 32 | AI2: 33 | AJ2: 34 | AK2: 35 | AL2: 36
A3: Year | C3: 1 | D3: 1 | E3: 1 | F3: 1 | G3: 1 | H3: 1 | I3: 1 | J3: 1 | K3: 1 | L3: 1 | M3: 1 | N3: 1 | O3: 2 | P3: 2 | Q3: 2 | R3: 2 | S3: 2 | T3: 2 | U3: 2 | V3: 2 | W3: 2 | X3: 2 | Y3: 2 | Z3: 2 | AA3: 3 | AB3: 3 | AC3: 3 | AD3: 3 | AE3: 3 | AF3: 3 | AG3: 3 | AH3: 3 | AI3: 3 | AJ3: 3 | AK3: 3 | AL3: 3
A5: Active installs | C5: =Assumptions!$D$5 | D5: =C5*(1+Assumptions!$D$6*POWER(Assumptions!$D$11,D2-1)) | E5: =D5*(1+Assumptions!$D$6*POWER(Assumptions!$D$11,E2-1)) | F5: =E5*(1+Assumptions!$D$6*POWER(Assumptions!$D$11,F2-1)) | G5: =F5*(1+Assumptions!$D$6*POWER(Assumptions!$D$11,G2-1)) | H5: =G5*(1+Assumptions!$D$6*POWER(Assumptions!$D$11,H2-1)) | I5: =H5*(1+Assumptions!$D$6*POWER(Assumptions!$D$11,I2-1)) | J5: =I5*(1+Assumptions!$D$6*POWER(Assumptions!$D$11,J2-1)) | K5: =J5*(1+Assumptions!$D$6*POWER(Assumptions!$D$11,K2-1)) | ... AL5: =AK5*(1+Assumptions!$D$6*POWER(Assumptions!$D$11,AL2-1))
A6: Email subscribers | C6: =Assumptions!$D$7 | D6: =C6*(1+Assumptions!$D$8*POWER(Assumptions!$D$11,D2-1)) | E6: =D6*(1+Assumptions!$D$8*POWER(Assumptions!$D$11,E2-1)) | F6: =E6*(1+Assumptions!$D$8*POWER(Assumptions!$D$11,F2-1)) | G6: =F6*(1+Assumptions!$D$8*POWER(Assumptions!$D$11,G2-1)) | H6: =G6*(1+Assumptions!$D$8*POWER(Assumptions!$D$11,H2-1)) | I6: =H6*(1+Assumptions!$D$8*POWER(Assumptions!$D$11,I2-1)) | J6: =I6*(1+Assumptions!$D$8*POWER(Assumptions!$D$11,J2-1)) | K6: =J6*(1+Assumptions!$D$8*POWER(Assumptions!$D$11,K2-1)) | ... AL6: =AK6*(1+Assumptions!$D$8*POWER(Assumptions!$D$11,AL2-1))
A7: Service leads / mo | C7: =Assumptions!$D$9 | D7: =C7*(1+Assumptions!$D$10*POWER(Assumptions!$D$11,D2-1)) | E7: =D7*(1+Assumptions!$D$10*POWER(Assumptions!$D$11,E2-1)) | F7: =E7*(1+Assumptions!$D$10*POWER(Assumptions!$D$11,F2-1)) | G7: =F7*(1+Assumptions!$D$10*POWER(Assumptions!$D$11,G2-1)) | H7: =G7*(1+Assumptions!$D$10*POWER(Assumptions!$D$11,H2-1)) | I7: =H7*(1+Assumptions!$D$10*POWER(Assumptions!$D$11,I2-1)) | J7: =I7*(1+Assumptions!$D$10*POWER(Assumptions!$D$11,J2-1)) | K7: =J7*(1+Assumptions!$D$10*POWER(Assumptions!$D$11,K2-1)) | ... AL7: =AK7*(1+Assumptions!$D$10*POWER(Assumptions!$D$11,AL2-1))
A9: [A] New supporter payers | C9: =C5*Assumptions!$D$12 | D9: =D5*Assumptions!$D$12 | E9: =E5*Assumptions!$D$12 | F9: =F5*Assumptions!$D$12 | G9: =G5*Assumptions!$D$12 | H9: =H5*Assumptions!$D$12 | I9: =I5*Assumptions!$D$12 | J9: =J5*Assumptions!$D$12 | ... AL9: =AL5*Assumptions!$D$12
A10: [A] Supporter revenue | C10: =C9*Assumptions!$D$13 | D10: =D9*Assumptions!$D$13 | E10: =E9*Assumptions!$D$13 | F10: =F9*Assumptions!$D$13 | G10: =G9*Assumptions!$D$13 | H10: =H9*Assumptions!$D$13 | I10: =I9*Assumptions!$D$13 | J10: =J9*Assumptions!$D$13 | ... AL10: =AL9*Assumptions!$D$13
A12: [B] Pro trials | C12: =IF(C2>=Assumptions!$D$15,C5*Assumptions!$D$16,0) | D12: =IF(D2>=Assumptions!$D$15,D5*Assumptions!$D$16,0) | E12: =IF(E2>=Assumptions!$D$15,E5*Assumptions!$D$16,0) | F12: =IF(F2>=Assumptions!$D$15,F5*Assumptions!$D$16,0) | G12: =IF(G2>=Assumptions!$D$15,G5*Assumptions!$D$16,0) | H12: =IF(H2>=Assumptions!$D$15,H5*Assumptions!$D$16,0) | I12: =IF(I2>=Assumptions!$D$15,I5*Assumptions!$D$16,0) | J12: =IF(J2>=Assumptions!$D$15,J5*Assumptions!$D$16,0) | ... AL12: =IF(AL2>=Assumptions!$D$15,AL5*Assumptions!$D$16,0)
A13: [B] New paid seats | C13: =C12*Assumptions!$D$17 | D13: =D12*Assumptions!$D$17 | E13: =E12*Assumptions!$D$17 | F13: =F12*Assumptions!$D$17 | G13: =G12*Assumptions!$D$17 | H13: =H12*Assumptions!$D$17 | I13: =I12*Assumptions!$D$17 | J13: =J12*Assumptions!$D$17 | ... AL13: =AL12*Assumptions!$D$17
A14: [B] Active paid seats | C14: =C13 | D14: =C14*(1-Assumptions!$D$19)+D13 | E14: =D14*(1-Assumptions!$D$19)+E13 | F14: =E14*(1-Assumptions!$D$19)+F13 | G14: =F14*(1-Assumptions!$D$19)+G13 | H14: =G14*(1-Assumptions!$D$19)+H13 | I14: =H14*(1-Assumptions!$D$19)+I13 | J14: =I14*(1-Assumptions!$D$19)+J13 | K14: =J14*(1-Assumptions!$D$19)+K13 | ... AL14: =AK14*(1-Assumptions!$D$19)+AL13
A15: [B] Pro MRR | C15: =C14*Assumptions!$D$18 | D15: =D14*Assumptions!$D$18 | E15: =E14*Assumptions!$D$18 | F15: =F14*Assumptions!$D$18 | G15: =G14*Assumptions!$D$18 | H15: =H14*Assumptions!$D$18 | I15: =I14*Assumptions!$D$18 | J15: =J14*Assumptions!$D$18 | ... AL15: =AL14*Assumptions!$D$18
A17: [C] Cloud MRR | C17: =IF(C2>=Assumptions!$D$21,C14*Assumptions!$D$22*Assumptions!$D$23,0) | D17: =IF(D2>=Assumptions!$D$21,D14*Assumptions!$D$22*Assumptions!$D$23,0) | E17: =IF(E2>=Assumptions!$D$21,E14*Assumptions!$D$22*Assumptions!$D$23,0) | F17: =IF(F2>=Assumptions!$D$21,F14*Assumptions!$D$22*Assumptions!$D$23,0) | G17: =IF(G2>=Assumptions!$D$21,G14*Assumptions!$D$22*Assumptions!$D$23,0) | H17: =IF(H2>=Assumptions!$D$21,H14*Assumptions!$D$22*Assumptions!$D$23,0) | I17: =IF(I2>=Assumptions!$D$21,I14*Assumptions!$D$22*Assumptions!$D$23,0) | J17: =IF(J2>=Assumptions!$D$21,J14*Assumptions!$D$22*Assumptions!$D$23,0) | ... AL17: =IF(AL2>=Assumptions!$D$21,AL14*Assumptions!$D$22*Assumptions!$D$23,0)
A19: [E] New community members | C19: =C6*Assumptions!$D$25 | D19: =D6*Assumptions!$D$25 | E19: =E6*Assumptions!$D$25 | F19: =F6*Assumptions!$D$25 | G19: =G6*Assumptions!$D$25 | H19: =H6*Assumptions!$D$25 | I19: =I6*Assumptions!$D$25 | J19: =J6*Assumptions!$D$25 | ... AL19: =AL6*Assumptions!$D$25
A20: [E] Active community | C20: =C19 | D20: =C20*(1-Assumptions!$D$27)+D19 | E20: =D20*(1-Assumptions!$D$27)+E19 | F20: =E20*(1-Assumptions!$D$27)+F19 | G20: =F20*(1-Assumptions!$D$27)+G19 | H20: =G20*(1-Assumptions!$D$27)+H19 | I20: =H20*(1-Assumptions!$D$27)+I19 | J20: =I20*(1-Assumptions!$D$27)+J19 | K20: =J20*(1-Assumptions!$D$27)+K19 | ... AL20: =AK20*(1-Assumptions!$D$27)+AL19
A21: [E] Community MRR | C21: =C20*Assumptions!$D$26 | D21: =D20*Assumptions!$D$26 | E21: =E20*Assumptions!$D$26 | F21: =F20*Assumptions!$D$26 | G21: =G20*Assumptions!$D$26 | H21: =H20*Assumptions!$D$26 | I21: =I20*Assumptions!$D$26 | J21: =J20*Assumptions!$D$26 | ... AL21: =AL20*Assumptions!$D$26
A22: [E] Course revenue | C22: =C6*Assumptions!$D$28*Assumptions!$D$29 | D22: =D6*Assumptions!$D$28*Assumptions!$D$29 | E22: =E6*Assumptions!$D$28*Assumptions!$D$29 | F22: =F6*Assumptions!$D$28*Assumptions!$D$29 | G22: =G6*Assumptions!$D$28*Assumptions!$D$29 | H22: =H6*Assumptions!$D$28*Assumptions!$D$29 | I22: =I6*Assumptions!$D$28*Assumptions!$D$29 | J22: =J6*Assumptions!$D$28*Assumptions!$D$29 | ... AL22: =AL6*Assumptions!$D$28*Assumptions!$D$29
A24: [D] Discovery calls | C24: =C7*Assumptions!$D$31 | D24: =D7*Assumptions!$D$31 | E24: =E7*Assumptions!$D$31 | F24: =F7*Assumptions!$D$31 | G24: =G7*Assumptions!$D$31 | H24: =H7*Assumptions!$D$31 | I24: =I7*Assumptions!$D$31 | J24: =J7*Assumptions!$D$31 | ... AL24: =AL7*Assumptions!$D$31
A25: [D] New projects | C25: =C24*Assumptions!$D$32 | D25: =D24*Assumptions!$D$32 | E25: =E24*Assumptions!$D$32 | F25: =F24*Assumptions!$D$32 | G25: =G24*Assumptions!$D$32 | H25: =H24*Assumptions!$D$32 | I25: =I24*Assumptions!$D$32 | J25: =J24*Assumptions!$D$32 | ... AL25: =AL24*Assumptions!$D$32
A26: [D] Project revenue | C26: =C25*Assumptions!$D$33 | D26: =D25*Assumptions!$D$33 | E26: =E25*Assumptions!$D$33 | F26: =F25*Assumptions!$D$33 | G26: =G25*Assumptions!$D$33 | H26: =H25*Assumptions!$D$33 | I26: =I25*Assumptions!$D$33 | J26: =J25*Assumptions!$D$33 | ... AL26: =AL25*Assumptions!$D$33
A27: [D] New retainers | C27: =C25*Assumptions!$D$34 | D27: =D25*Assumptions!$D$34 | E27: =E25*Assumptions!$D$34 | F27: =F25*Assumptions!$D$34 | G27: =G25*Assumptions!$D$34 | H27: =H25*Assumptions!$D$34 | I27: =I25*Assumptions!$D$34 | J27: =J25*Assumptions!$D$34 | ... AL27: =AL25*Assumptions!$D$34
A28: [D] Active retainers | C28: =C27 | D28: =C28*(1-Assumptions!$D$36)+D27 | E28: =D28*(1-Assumptions!$D$36)+E27 | F28: =E28*(1-Assumptions!$D$36)+F27 | G28: =F28*(1-Assumptions!$D$36)+G27 | H28: =G28*(1-Assumptions!$D$36)+H27 | I28: =H28*(1-Assumptions!$D$36)+I27 | J28: =I28*(1-Assumptions!$D$36)+J27 | K28: =J28*(1-Assumptions!$D$36)+K27 | ... AL28: =AK28*(1-Assumptions!$D$36)+AL27
A29: [D] Retainer MRR | C29: =C28*Assumptions!$D$35 | D29: =D28*Assumptions!$D$35 | E29: =E28*Assumptions!$D$35 | F29: =F28*Assumptions!$D$35 | G29: =G28*Assumptions!$D$35 | H29: =H28*Assumptions!$D$35 | I29: =I28*Assumptions!$D$35 | J29: =J28*Assumptions!$D$35 | ... AL29: =AL28*Assumptions!$D$35
A31: TOTAL monthly revenue | C31: =C10+C15+C17+C21+C22+C26+C29 | D31: =D10+D15+D17+D21+D22+D26+D29 | E31: =E10+E15+E17+E21+E22+E26+E29 | F31: =F10+F15+F17+F21+F22+F26+F29 | G31: =G10+G15+G17+G21+G22+G26+G29 | H31: =H10+H15+H17+H21+H22+H26+H29 | I31: =I10+I15+I17+I21+I22+I26+I29 | J31: =J10+J15+J17+J21+J22+J26+J29 | ... AL31: =AL10+AL15+AL17+AL21+AL22+AL26+AL29
A32: Recurring MRR | C32: =C15+C17+C21+C29 | D32: =D15+D17+D21+D29 | E32: =E15+E17+E21+E29 | F32: =F15+F17+F21+F29 | G32: =G15+G17+G21+G29 | H32: =H15+H17+H21+H29 | I32: =I15+I17+I21+I29 | J32: =J15+J17+J21+J29 | ... AL32: =AL15+AL17+AL21+AL29
A33: Cumulative revenue | C33: =C31 | D33: =C33+D31 | E33: =D33+E31 | F33: =E33+F31 | G33: =F33+G31 | H33: =G33+H31 | I33: =H33+I31 | J33: =I33+J31 | K33: =J33+K31 | ... AL33: =AK33+AL31
A35: mix: Supporter | C35: =C10 | D35: =D10 | E35: =E10 | F35: =F10 | G35: =G10 | H35: =H10 | I35: =I10 | J35: =J10 | ... AL35: =AL10
A36: mix: Pro | C36: =C15 | D36: =D15 | E36: =E15 | F36: =F15 | G36: =G15 | H36: =H15 | I36: =I15 | J36: =J15 | ... AL36: =AL15
A37: mix: Cloud | C37: =C17 | D37: =D17 | E37: =E17 | F37: =F17 | G37: =G17 | H37: =H17 | I37: =I17 | J37: =J17 | ... AL37: =AL17
A38: mix: Content | C38: =C21+C22 | D38: =D21+D22 | E38: =E21+E22 | F38: =F21+F22 | G38: =G21+G22 | H38: =H21+H22 | I38: =I21+I22 | J38: =J21+J22 | ... AL38: =AL21+AL22
A39: mix: Services | C39: =C26+C29 | D39: =D26+D29 | E39: =E26+E29 | F39: =F26+F29 | G39: =G26+G29 | H39: =H26+H29 | I39: =I26+I29 | J39: =J26+J29 | ... AL39: =AL26+AL29
